[{"date":"Sat, 15 Nov 2014 04:35:46 GMT","sloc":53,"lloc":31,"functions":7,"deliveredBugs":0.2406988502393643,"maintainability":74.84273875941862,"lintErrors":1,"difficulty":7.384615384615385},{"date":"Sat, 15 Nov 2014 04:35:50 GMT","sloc":53,"lloc":31,"functions":7,"deliveredBugs":0.2406988502393643,"maintainability":74.84273875941862,"lintErrors":1,"difficulty":7.384615384615385},{"date":"Sat, 15 Nov 2014 04:40:45 GMT","sloc":53,"lloc":31,"functions":7,"deliveredBugs":0.2406988502393643,"maintainability":74.84273875941862,"lintErrors":1,"difficulty":7.384615384615385},{"date":"Sat, 15 Nov 2014 04:42:15 GMT","sloc":53,"lloc":31,"functions":7,"deliveredBugs":0.24760000419863798,"maintainability":74.47693262755539,"lintErrors":[],"difficulty":8.423076923076923},{"date":"Sat, 15 Nov 2014 05:02:56 GMT","sloc":53,"lloc":31,"functions":7,"deliveredBugs":0.24760000419863798,"maintainability":74.47693262755539,"lintErrors":[],"difficulty":8.423076923076923}]